seven_ewa_app/__init__.py
seven_ewa_app/handlers/__init__.py
seven_ewa_app/handlers/ewa_app_base.py
seven_ewa_app/handlers/qqmini_helper.py
seven_ewa_app/models/__init__.py
seven_ewa_app/models/enum.py
seven_ewa_app/utils/__init__.py
seven_ewa_app/utils/daily_refresh_util.py
seven_ewa_app/utils/dict.py
seven_ewa_app/utils/json_util.py
seven_ewa_app/utils/jwt_util.py
seven_ewa_app/utils/redis_util.py
seven_ewa_app/utils/snowflake.py
seven_ewa_app-1.0.2.dist-info/METADATA
seven_ewa_app-1.0.2.dist-info/WHEEL
seven_ewa_app-1.0.2.dist-info/top_level.txt
seven_ewa_app-1.0.2.dist-info/RECORD
