Metadata-Version: 2.1
Name: seven-ewa-app
Version: 1.0.2
Summary: seven ewa app
Home-page: UNKNOWN
Author: seven
Author-email: tech@gao7.com
License: MIT
Platform: UNKNOWN
Classifier: Topic :: Software Development :: Libraries :: Python Modules
Classifier: Programming Language :: Python
Classifier: Programming Language :: Python :: 3.4
Classifier: Programming Language :: Python :: 3.5
Classifier: Programming Language :: Python :: 3.6
Classifier: Programming Language :: Python :: 3.7
Classifier: Programming Language :: Python :: 3.8
Classifier: Programming Language :: Python :: 3.9
Requires-Python: ~=3.4
Requires-Dist: seven-framework (>=1.0.108)
Requires-Dist: emoji (>=1.2.0)
Requires-Dist: PyJWT (==1.7.1)
